trading_data_client/README.md
trading_data_client/__init__.py
trading_data_client/client.py
trading_data_client/config.py
trading_data_client/exceptions.py
trading_data_client/historical.py
trading_data_client/models.py
trading_data_client/py.typed
trading_data_client/stream.py
trading_data_client/utils.py
trading_data_client-0.1.0.dist-info/licenses/LICENSE
trading_data_client-0.1.0.dist-info/METADATA
trading_data_client-0.1.0.dist-info/WHEEL
trading_data_client-0.1.0.dist-info/top_level.txt
trading_data_client-0.1.0.dist-info/RECORD
