Metadata-Version: 2.4
Name: trading-data-client
Version: 0.1.0
Summary: Python client library for Trading Data Server - fetch historical and real-time market data
Home-page: https://github.com/benjamincham/moonbase_Datahub
Author: Benjamin Cham
Author-email: Benjamin Cham <benjamincham@users.noreply.github.com>
License: MIT
Project-URL: Homepage, https://github.com/benjamincham/moonbase_Datahub
Project-URL: Documentation, https://github.com/benjamincham/moonbase_Datahub#readme
Project-URL: Repository, https://github.com/benjamincham/moonbase_Datahub
Project-URL: Bug Tracker, https://github.com/benjamincham/moonbase_Datahub/issues
Keywords: trading,market-data,ohlcv,real-time,streaming,alpaca,yfinance,historical-data
Classifier: Development Status :: 3 - Alpha
Classifier: Intended Audience :: Developers
Classifier: Intended Audience :: Financial and Insurance Industry
Classifier: License :: OSI Approved :: MIT License
Classifier: Programming Language :: Python :: 3
Classifier: Programming Language :: Python :: 3.10
Classifier: Programming Language :: Python :: 3.11
Classifier: Programming Language :: Python :: 3.12
Classifier: Topic :: Office/Business :: Financial
Classifier: Topic :: Software Development :: Libraries :: Python Modules
Classifier: Operating System :: OS Independent
Requires-Python: >=3.10
License-File: LICENSE
Requires-Dist: requests>=2.28.0
Requires-Dist: pyzmq>=25.0.0
Requires-Dist: pydantic>=2.0.0
Requires-Dist: python-dateutil>=2.8.0
Provides-Extra: dev
Requires-Dist: pytest>=7.0.0; extra == "dev"
Requires-Dist: pytest-cov>=4.0.0; extra == "dev"
Requires-Dist: pytest-mock>=3.10.0; extra == "dev"
Requires-Dist: responses>=0.22.0; extra == "dev"
Requires-Dist: mypy>=1.0.0; extra == "dev"
Requires-Dist: flake8>=6.0.0; extra == "dev"
Requires-Dist: black>=23.0.0; extra == "dev"
Dynamic: author
Dynamic: home-page
Dynamic: license-file
Dynamic: requires-python
